quisca/__init__.py
quisca-0.1.1.dist-info/LICENSE
quisca-0.1.1.dist-info/METADATA
quisca-0.1.1.dist-info/WHEEL
quisca-0.1.1.dist-info/entry_points.txt
quisca-0.1.1.dist-info/top_level.txt
quisca-0.1.1.dist-info/RECORD
