Metadata-Version: 2.1
Name: quisca
Version: 0.1.1
Summary: Score Aggregator for Quizizz
Author-email: Ashvin V <acedeveloper003@gmail.com>
License: MIT License
Project-URL: homepage, https://github.com/acedev003/quisca
Project-URL: repository, https://github.com/Acedev003/QuiScA.git
Keywords: Quizizz,quiz,joinmyquiz,aggregator
Classifier: Development Status :: 3 - Alpha
Classifier: Environment :: Console
Classifier: Intended Audience :: Education
Classifier: Intended Audience :: End Users/Desktop
Classifier: License :: OSI Approved :: MIT License
Classifier: Programming Language :: Python :: 3.8
Requires-Python: >=3.8
License-File: LICENSE
Requires-Dist: pandas
Requires-Dist: openpyxl
Requires-Dist: tabulate
